better_coverage/__init__.py
better_coverage/plugin.py
better_coverage/py.typed
better_coverage-1.0.0.dist-info/licenses/LICENSE
better_coverage-1.0.0.dist-info/METADATA
better_coverage-1.0.0.dist-info/WHEEL
better_coverage-1.0.0.dist-info/entry_points.txt
better_coverage-1.0.0.dist-info/top_level.txt
better_coverage-1.0.0.dist-info/RECORD
