Metadata-Version: 2.4
Name: better-coverage
Version: 1.0.0
Summary: Pytest reporter displaying pytest-cov coverage in Jest/Istanbul format with directory tree
Author-email: Mridang Agarwalla <mridang.agarwalla@gmail.com>
Maintainer-email: Mridang Agarwalla <mridang.agarwalla@gmail.com>
License: Apache-2.0
Project-URL: homepage, https://github.com/mridang/pytest-reporters
Project-URL: repository, https://github.com/mridang/pytest-reporters
Project-URL: documentation, https://github.com/mridang/pytest-reporters
Project-URL: Bug Tracker, https://github.com/mridang/pytest-reporters/issues
Keywords: pytest,coverage,istanbul,jest,reporter,pytest-plugin,coverage-reporter
Classifier: Topic :: Software Development :: Libraries
Classifier: Framework :: Pytest
Requires-Python: !=3.9.0,!=3.9.1,>=3.9
License-File: LICENSE
Requires-Dist: pytest>=7.0.0
Requires-Dist: pytest-cov>=2.8.1
Dynamic: license-file
